svg_path_editor/__init__.py
svg_path_editor/path_change_origin.py
svg_path_editor/path_operations.py
svg_path_editor/path_parser.py
svg_path_editor/py.typed
svg_path_editor/sub_path_bounds.py
svg_path_editor/svg.py
svg_path_editor-2.0.0.dist-info/licenses/License
svg_path_editor-2.0.0.dist-info/.gitignore
svg_path_editor-2.0.0.dist-info/METADATA
svg_path_editor-2.0.0.dist-info/WHEEL
svg_path_editor-2.0.0.dist-info/top_level.txt
svg_path_editor-2.0.0.dist-info/RECORD
