Metadata-Version: 2.4
Name: svg_path_editor
Version: 2.0.0
Summary: An SVG path editor
Author-email: Kurt Böhm <kurbo96@gmail.de>
License-Expression: MPL-2.0
Project-URL: Repository, https://github.com/KurtBoehm/svg_path_editor
Keywords: svg,drawing,vector
Classifier: Intended Audience :: Developers
Classifier: Programming Language :: Python :: 3
Classifier: Programming Language :: Python :: 3.12
Classifier: Programming Language :: Python :: 3.13
Classifier: Topic :: Software Development
Requires-Python: >=3.12
License-File: License
Provides-Extra: dev
Requires-Dist: furo; extra == "dev"
Requires-Dist: pytest; extra == "dev"
Requires-Dist: sphinx; extra == "dev"
Requires-Dist: sphinx-autoapi; extra == "dev"
Dynamic: license-file
